[{"__symbolic":"module","version":4,"metadata":{"Slider":{"__symbolic":"class","decorators":[{"__symbolic":"call","expression":{"__symbolic":"reference","module":"@angular/core","name":"Component","line":46,"character":1},"arguments":[{"selector":"ibm-slider","template":"\n\t\t<ng-container *ngIf=\"!skeleton; else skeletonTemplate\">\n\t\t\t<div\n\t\t\t\tclass=\"bx--slider\"\n\t\t\t\t[ngClass]=\"{'bx--slider--disabled': disabled}\">\n\t\t\t\t<div\n\t\t\t\t\t#thumb\n\t\t\t\t\tclass=\"bx--slider__thumb\"\n\t\t\t\t\ttabindex=\"0\"\n\t\t\t\t\t[ngStyle]=\"{'left.%': getFractionComplete() * 100}\"\n\t\t\t\t\t(mousedown)=\"onMouseDown($event)\"\n\t\t\t\t\t(keydown)=\"onKeyDown($event)\">\n\t\t\t\t</div>\n\t\t\t\t<div\n\t\t\t\t\t#track\n\t\t\t\t\tclass=\"bx--slider__track\"\n\t\t\t\t\t(click)=\"onClick($event)\">\n\t\t\t\t</div>\n\t\t\t\t<div\n\t\t\t\t\tclass=\"bx--slider__filled-track\"\n\t\t\t\t\t[ngStyle]=\"{transform: 'translate(0%, -50%)' + scaleX(getFractionComplete())}\">\n\t\t\t\t</div>\n\t\t\t\t<input\n\t\t\t\t\t#range\n\t\t\t\t\taria-label=\"slider\"\n\t\t\t\t\tclass=\"bx--slider__input\"\n\t\t\t\t\ttype=\"range\"\n\t\t\t\t\t[step]=\"step\"\n\t\t\t\t\t[min]=\"min\"\n\t\t\t\t\t[max]=\"max\"\n\t\t\t\t\t[value]=\"value\">\n\t\t\t</div>\n\t\t\t<label [id]=\"bottomRangeId\" class=\"bx--slider__range-label\">\n\t\t\t\t<ng-content select=\"[minLabel]\"></ng-content>\n\t\t\t</label>\n\t\t\t<label [id]=\"topRangeId\" class=\"bx--slider__range-label\">\n\t\t\t\t<ng-content select=\"[maxLabel]\"></ng-content>\n\t\t\t</label>\n\t\t\t<ng-content select=\"input\"></ng-content>\n\t\t</ng-container>\n\n\t\t<ng-template #skeletonTemplate>\n\t\t\t<div class=\"bx--form-item\">\n\t\t\t\t<label class=\"bx--label bx--skeleton\"></label>\n\t\t\t\t<div class=\"bx--slider-container bx--skeleton\">\n\t\t\t\t\t<span class=\"bx--slider__range-label\"></span>\n\t\t\t\t\t<div class=\"bx--slider\">\n\t\t\t\t\t\t<div class=\"bx--slider__thumb\"></div>\n\t\t\t\t\t\t<div class=\"bx--slider__track\"></div>\n\t\t\t\t\t\t<div class=\"bx--slider__filled-track\"></div>\n\t\t\t\t\t</div>\n\t\t\t\t\t<span class=\"bx--slider__range-label\"></span>\n\t\t\t\t</div>\n\t\t\t</div>\n\t\t</ng-template>\n\t","providers":[{"provide":{"__symbolic":"reference","module":"@angular/forms","name":"NG_VALUE_ACCESSOR","line":106,"character":12},"useExisting":{"__symbolic":"reference","name":"Slider"},"multi":true}]}]}],"members":{"min":[{"__symbolic":"property","decorators":[{"__symbolic":"call","expression":{"__symbolic":"reference","module":"@angular/core","name":"Input","line":116,"character":2}}]}],"max":[{"__symbolic":"property","decorators":[{"__symbolic":"call","expression":{"__symbolic":"reference","module":"@angular/core","name":"Input","line":118,"character":2}}]}],"step":[{"__symbolic":"property","decorators":[{"__symbolic":"call","expression":{"__symbolic":"reference","module":"@angular/core","name":"Input","line":120,"character":2}}]}],"value":[{"__symbolic":"property","decorators":[{"__symbolic":"call","expression":{"__symbolic":"reference","module":"@angular/core","name":"Input","line":122,"character":2}}]}],"id":[{"__symbolic":"property","decorators":[{"__symbolic":"call","expression":{"__symbolic":"reference","module":"@angular/core","name":"Input","line":146,"character":2}}]}],"shiftMultiplier":[{"__symbolic":"property","decorators":[{"__symbolic":"call","expression":{"__symbolic":"reference","module":"@angular/core","name":"Input","line":148,"character":2}}]}],"skeleton":[{"__symbolic":"property","decorators":[{"__symbolic":"call","expression":{"__symbolic":"reference","module":"@angular/core","name":"Input","line":150,"character":2}}]}],"disableArrowKeys":[{"__symbolic":"property","decorators":[{"__symbolic":"call","expression":{"__symbolic":"reference","module":"@angular/core","name":"Input","line":152,"character":2}}]}],"disabled":[{"__symbolic":"property","decorators":[{"__symbolic":"call","expression":{"__symbolic":"reference","module":"@angular/core","name":"Input","line":154,"character":2}}]}],"valueChange":[{"__symbolic":"property","decorators":[{"__symbolic":"call","expression":{"__symbolic":"reference","module":"@angular/core","name":"Output","line":167,"character":2}}]}],"hostClass":[{"__symbolic":"property","decorators":[{"__symbolic":"call","expression":{"__symbolic":"reference","module":"@angular/core","name":"HostBinding","line":168,"character":2},"arguments":["class.bx--slider-container"]}]}],"thumb":[{"__symbolic":"property","decorators":[{"__symbolic":"call","expression":{"__symbolic":"reference","module":"@angular/core","name":"ViewChild","line":169,"character":2},"arguments":["thumb"]}]}],"track":[{"__symbolic":"property","decorators":[{"__symbolic":"call","expression":{"__symbolic":"reference","module":"@angular/core","name":"ViewChild","line":170,"character":2},"arguments":["track"]}]}],"range":[{"__symbolic":"property","decorators":[{"__symbolic":"call","expression":{"__symbolic":"reference","module":"@angular/core","name":"ViewChild","line":171,"character":2},"arguments":["range"]}]}],"__ctor__":[{"__symbolic":"constructor","parameters":[{"__symbolic":"reference","module":"@angular/core","name":"ElementRef","line":184,"character":35}]}],"ngAfterViewInit":[{"__symbolic":"method"}],"ngOnDestroy":[{"__symbolic":"method"}],"registerOnChange":[{"__symbolic":"method"}],"registerOnTouched":[{"__symbolic":"method"}],"writeValue":[{"__symbolic":"method"}],"getFractionComplete":[{"__symbolic":"method"}],"scaleX":[{"__symbolic":"method"}],"convertToValue":[{"__symbolic":"method"}],"convertToPx":[{"__symbolic":"method"}],"incrementValue":[{"__symbolic":"method"}],"decrementValue":[{"__symbolic":"method"}],"onChange":[{"__symbolic":"method"}],"onClick":[{"__symbolic":"method"}],"onFocus":[{"__symbolic":"method"}],"onMouseMove":[{"__symbolic":"method"}],"onMouseDown":[{"__symbolic":"method"}],"onMouseUp":[{"__symbolic":"method"}],"onKeyDown":[{"__symbolic":"method"}]},"statics":{"count":0}}}}]